email_utils/__init__.py
email_utils/email_reader.py
email_utils_helpdesk-0.1.dist-info/METADATA
email_utils_helpdesk-0.1.dist-info/WHEEL
email_utils_helpdesk-0.1.dist-info/top_level.txt
email_utils_helpdesk-0.1.dist-info/RECORD
