Metadata-Version: 2.1
Name: email_utils_helpdesk
Version: 0.1
Summary: A simple package for email handling.
Author: Ali
Classifier: Programming Language :: Python :: 3
Classifier: License :: OSI Approved :: MIT License
